{
  "generatedAt": "2026-07-11T02:55:09.487Z",
  "count": 25,
  "items": [
    {
      "source": "Soompi",
      "title": "TXT&#8217;s Yeonjun Achieves Highest 1st-Day Sales Of Any Korean Soloist In 2026 With &#8220;NO LABELS: PART 02&#8221;",
      "link": "https://www.soompi.com/article/1853805wpp/txts-yeonjun-achieves-highest-1st-day-sales-of-any-korean-soloist-in-2026-with-no-labels-part-02",
      "date": "2026-07-11T02:33:57.000Z",
      "description": "It took TXT’s Yeonjun just one day to smash his personal first-week sales record with his latest release! On July 10 at 1 p.m. KST, Yeonjun made his highly-anticipated solo comeback with his new mini album “NO LABELS: PART 02.” According to",
      "groups": [
        "TXT"
      ]
    },
    {
      "source": "Reddit · r/kpop",
      "title": "BABYMONSTER - TAKE YOUR PICK with BABYMONSTERㅣHWAITING S6 EP.02 @ DIVE Studios (260710) [ENG SUB]",
      "link": "https://www.reddit.com/r/kpop/comments/1ut6sxn/babymonster_take_your_pick_with/",
      "date": "2026-07-11T01:45:47.000Z",
      "description": "",
      "groups": [
        "BABYMONSTER",
        "IVE"
      ]
    },
    {
      "source": "Reddit · r/kpop",
      "title": "XLOV - XLOV Revolutionizes K-Pop with a ‘Genderless’ Concept: ‘See the World from a Different Point of View’ (Exclusive) @ People Magazine (260710)",
      "link": "https://www.reddit.com/r/kpop/comments/1ut6r1m/xlov_xlov_revolutionizes_kpop_with_a_genderless/",
      "date": "2026-07-11T01:43:14.000Z",
      "description": "",
      "groups": [
        "IVE"
      ]
    },
    {
      "source": "Reddit · r/kpop",
      "title": "LE SSERAFIM - LE SSERAFIM: 'PUREFLOW', Pt. 1, \"ICONIC BY MISTAKE,\" and Working with KATSEYE | Zane Lowe Interview @ Apple Music (260711) [ENG SUB]",
      "link": "https://www.reddit.com/r/kpop/comments/1ut4l3g/le_sserafim_le_sserafim_pureflow_pt_1_iconic_by/",
      "date": "2026-07-11T00:03:03.000Z",
      "description": "",
      "groups": [
        "LE SSERAFIM"
      ]
    },
    {
      "source": "Reddit · r/kpop",
      "title": "aespa KARINA - PDs, please reveal your identities | Nah Yungsuk (Na PD) VS Junior Producer (Ep. 1 Behind the Scenes) (260707) [ENG SUB]",
      "link": "https://www.reddit.com/r/kpop/comments/1ut2nsg/aespa_karina_pds_please_reveal_your_identities/",
      "date": "2026-07-10T22:42:48.000Z",
      "description": "",
      "groups": [
        "aespa"
      ]
    },
    {
      "source": "Reddit · r/kpop",
      "title": "Red Velvet SEULGI - All This for 100K Won? SEULGI’s Summer Haul SEUL-tyling | SEUL-ffective Fit & Quality Guaranteed @ Hi Seulgi (260710) [ENG SUB]",
      "link": "https://www.reddit.com/r/kpop/comments/1ut2hfn/red_velvet_seulgi_all_this_for_100k_won_seulgis/",
      "date": "2026-07-10T22:35:37.000Z",
      "description": "",
      "groups": [
        "Red Velvet",
        "IVE"
      ]
    },
    {
      "source": "Reddit · r/kpop",
      "title": "SM Classics - SM CLASSICS LIVE 2026-2027 SEASON TOUR (Poster and Dates)",
      "link": "https://www.reddit.com/r/kpop/comments/1ut1tvl/sm_classics_sm_classics_live_20262027_season_tour/",
      "date": "2026-07-10T22:09:36.000Z",
      "description": "",
      "groups": [
        "IVE"
      ]
    },
    {
      "source": "Reddit · r/kpop",
      "title": "2026 TMElive International Music Awards - Artist Lineup",
      "link": "https://www.reddit.com/r/kpop/comments/1ut1ski/2026_tmelive_international_music_awards_artist/",
      "date": "2026-07-10T22:08:06.000Z",
      "description": "",
      "groups": [
        "IVE"
      ]
    },
    {
      "source": "Reddit · r/kpop",
      "title": "aespa - Would you like to go to heaven with me? @ aesParty EP.11 (260710) [ENG SUB]",
      "link": "https://www.reddit.com/r/kpop/comments/1ut1c9g/aespa_would_you_like_to_go_to_heaven_with_me/",
      "date": "2026-07-10T21:50:11.000Z",
      "description": "",
      "groups": [
        "aespa"
      ]
    },
    {
      "source": "Reddit · r/kpop",
      "title": "Lee Mujin signs exclusive contract with new label under Mound Media",
      "link": "https://www.reddit.com/r/kpop/comments/1usuuq2/lee_mujin_signs_exclusive_contract_with_new_label/",
      "date": "2026-07-10T17:49:53.000Z",
      "description": "",
      "groups": [
        "IVE"
      ]
    },
    {
      "source": "Reddit · r/kpop",
      "title": "ENHYPEN Attends U.S. 'Comic-Con'… \"Will Introduce Dark Moon Universe\"",
      "link": "https://www.reddit.com/r/kpop/comments/1usrj5z/enhypen_attends_us_comiccon_will_introduce_dark/",
      "date": "2026-07-10T15:51:05.000Z",
      "description": "",
      "groups": [
        "ENHYPEN",
        "IVE"
      ]
    },
    {
      "source": "Reddit · r/kpop",
      "title": "TXT (TOMORROW X TOGETHER) Yeonjun & Yeji (ITZY) - 'Ice Cream' Dance Challenge (260710)",
      "link": "https://www.reddit.com/r/kpop/comments/1usoqfn/txt_tomorrow_x_together_yeonjun_yeji_itzy_ice/",
      "date": "2026-07-10T14:07:41.000Z",
      "description": "",
      "groups": [
        "TXT",
        "ITZY"
      ]
    },
    {
      "source": "Reddit · r/kpop",
      "title": "Stray Kids - 10th Mini Album 'THIS & THAT' (Tracklist)",
      "link": "https://www.reddit.com/r/kpop/comments/1usokk1/stray_kids_10th_mini_album_this_that_tracklist/",
      "date": "2026-07-10T14:01:35.000Z",
      "description": "",
      "groups": [
        "Stray Kids"
      ]
    },
    {
      "source": "Reddit · r/kpop",
      "title": "ITZY Yuna will reportedly no longer be a part of Netflix’s upcoming series \"Do Not Cross The Wall\"",
      "link": "https://www.reddit.com/r/kpop/comments/1usl7m1/itzy_yuna_will_reportedly_no_longer_be_a_part_of/",
      "date": "2026-07-10T11:40:57.000Z",
      "description": "",
      "groups": [
        "ITZY"
      ]
    },
    {
      "source": "Soompi",
      "title": "Watch: ATEEZ Takes 2nd Win For &#8220;BAD&#8221; On &#8220;Music Bank&#8221;; Performances By Yeonjun, RESCENE, And More",
      "link": "https://www.soompi.com/article/1853750wpp/watch-ateez-takes-2nd-win-for-bad-on-music-bank-performances-by-yeonjun-rescene-and-more",
      "date": "2026-07-10T11:35:19.000Z",
      "description": "ATEEZ has won their second music show trophy for “BAD”! On the July 10 episode of “Music Bank,” the candidates for first place were SEVENTEEN’s V8’s “singasong” and ATEEZ&#8217;s &#8220;BAD.&#8221; ATEEZ ultimately took the prize with a tot",
      "groups": [
        "ATEEZ"
      ]
    },
    {
      "source": "Soompi",
      "title": "IVE&#8217;s Gaeul To Be Absent From 2026 TMElive International Music Awards (TIMA) Due To Scheduling Conflict",
      "link": "https://www.soompi.com/article/1853683wpp/ives-gaeul-to-be-absent-from-2026-tmelive-international-music-awards-tima-due-to-scheduling-conflict",
      "date": "2026-07-10T05:03:06.000Z",
      "description": "Gaeul will not be joining IVE at the upcoming 2026 TMElive International Music Awards (TIMA). On July 10, STARSHIP Entertainment announced that Gaeul will be unable to participate in IVE&#8217;s scheduled appearance at the 2026 TMElive Inte",
      "groups": [
        "IVE"
      ]
    },
    {
      "source": "Soompi",
      "title": "izna Announces First Stops For 2026 Tour &#8220;WHO DAT GIRL?&#8221;",
      "link": "https://www.soompi.com/article/1853677wpp/izna-announces-first-stops-for-2026-tour-who-dat-girl",
      "date": "2026-07-10T03:46:26.000Z",
      "description": "It’s official: izna is going on tour! On July 10, izna revealed the first set of stops for their upcoming “WHO DAT GIRL?” tour, which will kick off this fall. First, izna will kick things off with two nights of concerts in Seoul on Septembe",
      "groups": [
        "izna"
      ]
    },
    {
      "source": "Reddit · r/kpop",
      "title": "CHUU has concluded her exclusive contract with ATRP",
      "link": "https://www.reddit.com/r/kpop/comments/1usaud2/chuu_has_concluded_her_exclusive_contract_with/",
      "date": "2026-07-10T02:28:29.000Z",
      "description": "",
      "groups": [
        "IVE"
      ]
    },
    {
      "source": "Soompi",
      "title": "BTS&#8217;s Jin Talks About The Most Memorable World Tour Moment, What Music Has Given Him, And More",
      "link": "https://www.soompi.com/article/1853617wpp/btss-jin-talks-about-the-most-memorable-world-tour-moment-what-music-has-given-him-and-more",
      "date": "2026-07-10T02:19:16.000Z",
      "description": "BTS’s Jin sat down with ELLE Korea for a pictorial and interview! The shoot was a collaboration with Gucci, for which Jin serves as a global brand ambassador. Against the backdrop of a vintage hotel, he captivated with his restrained yet in",
      "groups": [
        "BTS",
        "IVE"
      ]
    },
    {
      "source": "Soompi",
      "title": "ITZY&#8217;s Yuna Is A Rising Actress Who Falls For Her Co-Star In New Drama &#8220;My Bias, My Boss&#8221;",
      "link": "https://www.soompi.com/article/1853591wpp/itzys-yuna-is-a-rising-actress-who-falls-for-her-co-star-in-new-drama-my-bias-my-boss",
      "date": "2026-07-10T00:56:00.000Z",
      "description": "tvN’s upcoming drama “My Bias, My Boss” has shared a sneak peek of ITZY’s Yuna in character! Based on the webtoon of the same name, “My Bias, My Boss” tells the story of the romance between Nam Da Reum, who joins a company to meet her longt",
      "groups": [
        "ITZY"
      ]
    },
    {
      "source": "Soompi",
      "title": "Watch: Stray Kids Introduces &#8220;TASY,&#8221; The Official Character For STAY",
      "link": "https://www.soompi.com/article/1853551wpp/watch-stray-kids-introduces-tasy-the-official-character-for-stay",
      "date": "2026-07-09T23:20:08.000Z",
      "description": "Meet “TASY,” Stray Kids’ official character for STAY! On July 10 at midnight KST, Stray Kids released an adorable video introducing a brand-new character to represent STAY, their official fandom. The whimsical new video features TASY meetin",
      "groups": [
        "Stray Kids"
      ]
    },
    {
      "source": "Soompi",
      "title": "aespa&#8217;s &#8220;Whiplash&#8221; Becomes Their Fastest MV To Hit 300 Million Views",
      "link": "https://www.soompi.com/article/1853539wpp/aespas-whiplash-becomes-their-fastest-mv-to-hit-300-million-views",
      "date": "2026-07-09T22:25:42.000Z",
      "description": "aespa has broken a personal record with their music video for “Whiplash”! On July 10 at around 6 a.m. KST, aespa’s music video for their 2024 hit “Whiplash” surpassed 300 million views on YouTube, making it their third music video to do so ",
      "groups": [
        "aespa"
      ]
    },
    {
      "source": "Soompi",
      "title": "Watch: LE SSERAFIM, ILLIT, And KATSEYE Take 2nd Win For &#8220;ICONIC BY MISTAKE&#8221; On &#8220;M Countdown&#8221;; Performances By i-dle, And More",
      "link": "https://www.soompi.com/article/1853509wpp/watch-le-sserafim-illit-and-katseye-takes-2nd-win-for-iconic-by-mistake-on-m-countdown-performances-by-i-dle-and-more",
      "date": "2026-07-09T12:20:45.000Z",
      "description": "LE SSERAFIM, ILLIT, and KATSEYE have won their second music show trophy for their collab single “ICONIC BY MISTAKE&#8220;! On the July 9 episode of &#8220;M Countdown,&#8221; the candidates for first place were LE SSERAFIM, ILLIT, and KATSE",
      "groups": [
        "LE SSERAFIM",
        "ILLIT"
      ]
    },
    {
      "source": "Soompi",
      "title": "ATEEZ And CORTIS Earn Double Crowns On Circle Weekly Charts",
      "link": "https://www.soompi.com/article/1853322wpp/ateez-and-cortis-earn-double-crowns-on-circle-weekly-charts",
      "date": "2026-07-08T21:02:27.000Z",
      "description": "Circle Chart has revealed its chart rankings for the week of June 21 to 27! Album Chart ATEEZ achieved a double crown on this week’s charts, topping both the physical album chart and the digital download chart with their new mini album “GOL",
      "groups": [
        "CORTIS",
        "ATEEZ"
      ]
    },
    {
      "source": "Soompi",
      "title": "KARD&#8217;s &#8220;Don&#8217;t Recall&#8221; Becomes Their 1st MV To Hit 100 Million Views",
      "link": "https://www.soompi.com/article/1853227wpp/kards-dont-recall-becomes-their-1st-mv-to-hit-100-million-views",
      "date": "2026-07-08T14:26:58.000Z",
      "description": "KARD has just hit the 100 million mark for the first time on YouTube! On July 8 at around 2 p.m. KST, KARD’s music video for their 2017 pre-debut single “Don’t Recall” surpassed 100 million views on YouTube, making it the group’s first musi",
      "groups": [
        "KARD"
      ]
    }
  ]
}